interpret/__init__.py
interpret/_version.py
interpret/develop.py
interpret/api/__init__.py
interpret/api/base.py
interpret/api/templates.py
interpret/blackbox/__init__.py
interpret/blackbox/_lime.py
interpret/blackbox/_partialdependence.py
interpret/blackbox/_permutationimportance.py
interpret/blackbox/_sensitivity.py
interpret/blackbox/_shap.py
interpret/data/__init__.py
interpret/data/_response.py
interpret/ext/__init__.py
interpret/ext/examples.py
interpret/ext/extension.py
interpret/ext/extension_utils.py
interpret/ext/blackbox/__init__.py
interpret/ext/data/__init__.py
interpret/ext/glassbox/__init__.py
interpret/ext/greybox/__init__.py
interpret/ext/perf/__init__.py
interpret/ext/provider/__init__.py
interpret/glassbox/__init__.py
interpret/glassbox/_aplr.py
interpret/glassbox/_decisiontree.py
interpret/glassbox/_linear.py
interpret/glassbox/_lineardiscriminantanalysis.py
interpret/glassbox/_naivebayes.py
interpret/glassbox/_skoperules.py
interpret/glassbox/_tan.py
interpret/glassbox/quadraticdiscriminantanalysis.py
interpret/glassbox/_ebm/__init__.py
interpret/glassbox/_ebm/_bin.py
interpret/glassbox/_ebm/_boost.py
interpret/glassbox/_ebm/_ebm.py
interpret/glassbox/_ebm/_json.py
interpret/glassbox/_ebm/_merge_ebms.py
interpret/glassbox/_ebm/_multiclass.py
interpret/glassbox/_ebm/_tensor.py
interpret/glassbox/_ebm/_utils.py
interpret/glassbox/_ebm/_research/__init__.py
interpret/glassbox/_ebm/_research/_group_importance.py
interpret/glassbox/nam/__init__.py
interpret/glassbox/nam/data/__init__.py
interpret/glassbox/nam/data/data.py
interpret/glassbox/nam/models/__init__.py
interpret/glassbox/nam/models/featurenn.py
interpret/glassbox/nam/models/nam.py
interpret/glassbox/nam/models/saver.py
interpret/glassbox/nam/models/utils.py
interpret/glassbox/nam/models/activation/__init__.py
interpret/glassbox/nam/models/activation/exu.py
interpret/glassbox/nam/models/activation/relu.py
interpret/glassbox/nam/trainer/__init__.py
interpret/glassbox/nam/trainer/losses.py
interpret_clone-0.1.2.dist-info/METADATA
interpret_clone-0.1.2.dist-info/WHEEL
interpret_clone-0.1.2.dist-info/top_level.txt
interpret_clone-0.1.2.dist-info/RECORD
